CHANGES.txt
CONTRIBUTORS.txt
README.txt
setup.py
Products/__init__.py
Products.ShibbolethPermissions.egg-info/PKG-INFO
Products.ShibbolethPermissions.egg-info/SOURCES.txt
Products.ShibbolethPermissions.egg-info/dependency_links.txt
Products.ShibbolethPermissions.egg-info/entry_points.txt
Products.ShibbolethPermissions.egg-info/namespace_packages.txt
Products.ShibbolethPermissions.egg-info/not-zip-safe
Products.ShibbolethPermissions.egg-info/requires.txt
Products.ShibbolethPermissions.egg-info/top_level.txt
Products/ShibbolethPermissions/README.txt
Products/ShibbolethPermissions/__init__.py
Products/ShibbolethPermissions/add-ShibbolethPermissions.zpt
Products/ShibbolethPermissions/config.zpt
Products/ShibbolethPermissions/configure.zcml
Products/ShibbolethPermissions/events.py
Products/ShibbolethPermissions/permissions.py
Products/ShibbolethPermissions/permissions.zcml
Products/ShibbolethPermissions/shibbolethlogin.gif
Products/ShibbolethPermissions/zmi.py
Products/ShibbolethPermissions/Extensions/Install.py
Products/ShibbolethPermissions/Extensions/__init__.py
Products/ShibbolethPermissions/browser/__init__.py
Products/ShibbolethPermissions/browser/configure.zcml
Products/ShibbolethPermissions/browser/permissions.py
Products/ShibbolethPermissions/browser/shibboleth.pt
Products/ShibbolethPermissions/docs/HISTORY.txt
Products/ShibbolethPermissions/docs/INSTALL.txt
Products/ShibbolethPermissions/docs/LICENSE.GPL
Products/ShibbolethPermissions/docs/LICENSE.txt
Products/ShibbolethPermissions/profiles/default/actions.xml
Products/ShibbolethPermissions/profiles/default/metadata.xml
Products/ShibbolethPermissions/tests/Selenium.html
Products/ShibbolethPermissions/tests/ShibbolethPermissions.txt
Products/ShibbolethPermissions/tests/TestBrowsers.txt
Products/ShibbolethPermissions/tests/__init__.py
Products/ShibbolethPermissions/tests/base.py
Products/ShibbolethPermissions/tests/test_adapter.py
Products/ShibbolethPermissions/tests/test_docstrings.py
Products/ShibbolethPermissions/tests/test_txtfiles.py
Products/ShibbolethPermissions/tests/test_views.py
Products/ShibbolethPermissions/tests/utils.py