Metadata-Version: 1.0
Name: Products.ShibbolethPermissions
Version: 0.8b2
Summary: Use shibboleth attributes as authenitcation information in Plone
Home-page: http://pypi.python.org/pypi/Products.ShibbolethPermissions/
Author: Tom Gross
Author-email: itconsense@gmail.com
License: GPL
Keywords: plone authentication shibboleth pas
Platform: UNKNOWN
Classifier: Framework :: Zope2
Classifier: Framework :: Plone
Classifier: Programming Language :: Python
